Logger/Logger.py
Logger/__init__.py
ilyxaaalogger-1.0.0.dist-info/METADATA
ilyxaaalogger-1.0.0.dist-info/WHEEL
ilyxaaalogger-1.0.0.dist-info/top_level.txt
ilyxaaalogger-1.0.0.dist-info/RECORD
